hrflow_connectors/__init__.py
hrflow_connectors/connectors/bullhorn/utils/authentication.py
hrflow_connectors/connectors/hrflow/schemas.py
hrflow_connectors/connectors/hrflow/warehouse.py
hrflow_connectors/core/__init__.py
hrflow_connectors/core/backend/__init__.py
hrflow_connectors/core/backend/common.py
hrflow_connectors/core/backend/localjson.py
hrflow_connectors/core/backend/s3.py
hrflow_connectors/core/connector.py
hrflow_connectors/core/documentation.py
hrflow_connectors/core/warehouse.py
hrflow_connectors/v1/__init__.py
hrflow_connectors/v1/connectors/abacusumantis/logo.jpeg
hrflow_connectors/v1/connectors/adpworkforcenow/logo.jpeg
hrflow_connectors/v1/connectors/adzuna/README.md
hrflow_connectors/v1/connectors/adzuna/__init__.py
hrflow_connectors/v1/connectors/adzuna/connector.py
hrflow_connectors/v1/connectors/adzuna/docs/pull_job_list.md
hrflow_connectors/v1/connectors/adzuna/logo.png
hrflow_connectors/v1/connectors/adzuna/mappings/format/pull_job_list.json
hrflow_connectors/v1/connectors/adzuna/notebooks/.gitkeep
hrflow_connectors/v1/connectors/adzuna/schemas.py
hrflow_connectors/v1/connectors/adzuna/test-config.yaml
hrflow_connectors/v1/connectors/adzuna/warehouse.py
hrflow_connectors/v1/connectors/afas/logo.png
hrflow_connectors/v1/connectors/agefiph/logo.png
hrflow_connectors/v1/connectors/apec/logo.png
hrflow_connectors/v1/connectors/applicantstack/logo.jpg
hrflow_connectors/v1/connectors/ashby/logo.png
hrflow_connectors/v1/connectors/avature/logo.jpeg
hrflow_connectors/v1/connectors/bamboohr/logo.png
hrflow_connectors/v1/connectors/beetween/logo.png
hrflow_connectors/v1/connectors/bite/logo.png
hrflow_connectors/v1/connectors/breezyhr/README.md
hrflow_connectors/v1/connectors/breezyhr/__init__.py
hrflow_connectors/v1/connectors/breezyhr/connector.py
hrflow_connectors/v1/connectors/breezyhr/docs/pull_job_list.md
hrflow_connectors/v1/connectors/breezyhr/docs/pull_profile_list.md
hrflow_connectors/v1/connectors/breezyhr/docs/push_profile_list.md
hrflow_connectors-4.27.4.dist-info/LICENSE
hrflow_connectors-4.27.4.dist-info/WHEEL
hrflow_connectors-4.27.4.dist-info/METADATA
hrflow_connectors-4.27.4.dist-info/RECORD
