Metadata-Version: 2.1
Name: hrflow-connectors
Version: 4.27.4
Summary: hrflow-connectors is an open source project created by HrFlow.ai to allow developers to connect easily HR ecosystem component.
Home-page: https://github.com/Riminder/hrflow-connectors
License: Apache-2.0
Author: HrFlow.ai
Author-email: support+hrflow_connectors@hrflow.ai
Requires-Python: >=3.9,<4.0
Classifier: License :: OSI Approved :: Apache Software License
Classifier: Programming Language :: Python :: 3
Classifier: Programming Language :: Python :: 3.9
Classifier: Programming Language :: Python :: 3.10
Classifier: Programming Language :: Python :: 3.11
Provides-Extra: s3
Requires-Dist: Jinja2 (>=3.0.3,<4.0.0)
Requires-Dist: beautifulsoup4 (==4.10.0)
Requires-Dist: boto3 (>=1.24.66,<2.0.0) ; extra == "s3"
Requires-Dist: hrflow (>=4.2.0,<5.0.0)
Requires-Dist: msgspec (>=0.18.6,<0.19.0)
Requires-Dist: mysql-connector-python (>=9.1.0,<10.0.0)
Requires-Dist: puremagic (>=1.27,<2.0)
Requires-Dist: pydantic (==1.10.8)
Requires-Dist: requests (>=2.27.1,<3.0.0)
Requires-Dist: simple-salesforce (>=1.12.4,<2.0.0)
Requires-Dist: smbprotocol (>=1.15.0,<2.0.0)
Requires-Dist: typing-extensions (>=4.7.1,<5.0.0)
Project-URL: Changelog, https://github.com/Riminder/hrflow-connectors/releases/
Project-URL: Documentation, https://github.com/Riminder/hrflow-connectors
Project-URL: HrFlow.ai Documentation, https://developers.hrflow.ai/
Project-URL: Repository, https://github.com/Riminder/hrflow-connectors
